Metadata-Version: 1.1
Name: gordon-alt
Version: 0.2.2
Summary: Gordon is a tool to create, wire and deploy AWS Lambdas using CloudFormation
Home-page: http://github.com/tjsail33/gordon-alt
Author: Tim Costa
Author-email: tjsail33@gmail.com
License: BSD
Keywords: aws lambda apigateway kinesis dynamodb s3 cloudwatch
Platform: any
Classifier: Programming Language :: Python :: 3
Classifier: Programming Language :: Python :: 2
Classifier: Development Status :: 4 - Beta
Classifier: Environment :: Web Environment
Classifier: Intended Audience :: Developers
Classifier: License :: OSI Approved :: BSD License
Classifier: Operating System :: OS Independent
Classifier: Topic :: Utilities
